{
  "replace": false,
  "values": [
    "minecraft:pillager_outposts",
    "minecraft:villages",
    {
      "id": "idas:labyrinth",
      "required": false
    },
    {
      "id": "idas:pillager_fortress",
      "required": false
    },
    {
      "id": "idas:ancient_mines",
      "required": false
    },
    {
      "id": "idas:bazaar",
      "required": false
    },
    {
      "id": "idas:tinkers_workshop",
      "required": false
    },
    {
      "id": "idas:nexus",
      "required": false
    },
    {
      "id": "idas:ruins_of_the_deep",
      "required": false
    },
    {
      "id": "idas:tree_of_wisdom",
      "required": false
    },
    {
      "id": "idas:iceandfire/dread_citadel",
      "required": false
    },
    {
      "id": "idas:tinkers_citadel",
      "required": false
    },
    {
      "id": "idas:ars_nouveau/archmages_tower",
      "required": false
    },
    {
      "id": "idas:desert_pyramid",
      "required": false
    },
    {
      "id": "idas:collectors_museum",
      "required": false
    },
    {
      "id": "idas:windswept_shrine",
      "required": false
    }
  ]
}